{
  "title": "👋 Welcome Back!",
  "message": "\n    <div style=\"font-family: Arial, sans-serif; line-height: 1.6; text-align: center;\">\n      <h2>Hello, Qatip User!</h2>\n      <p>We hope you are enjoying your experience with <b>Qatip</b>. 🚀</p>\n      <p>If you need any assistance, feel free to contact us at: \n        <a href=\"mailto:support@qatip.app\" style=\"color: #007BFF; text-decoration: underline;\">support@qatip.app</a>\n      </p>\n      <p>Best regards,<br><b>Qatip App Developer Team</b></p>\n    </div>\n  ",
  "type": "info",
  "category": "user-update",
  "priority": "normal",
  "icon": "smile",
  "url": "/dashboard",
  "actionText": "Go to Dashboard",
  "to": "user:2VIC9n52dqW8N3fp35XMBAlKoqp1",
  "isHtml": true
}